EasyMCDM/__init__.py
EasyMCDM/version.txt
EasyMCDM/models/Electre.py
EasyMCDM/models/Irmo.py
EasyMCDM/models/MCDM.py
EasyMCDM/models/Pareto.py
EasyMCDM/models/Promethee.py
EasyMCDM/models/WeightedSum.py
EasyMCDM/models/__init__.py
EasyMCDM/utils/__init__.py
EasyMCDM-0.5.13.dist-info/LICENSE
EasyMCDM-0.5.13.dist-info/METADATA
EasyMCDM-0.5.13.dist-info/WHEEL
EasyMCDM-0.5.13.dist-info/top_level.txt
EasyMCDM-0.5.13.dist-info/RECORD
