Metadata-Version: 2.1
Name: EasyMCDM
Version: 0.5.13
Summary: A easy to use Multi-Criteria Decision-Making (MCDM) toolkit which propose implementations for Electre, Promethee and much more.
Home-page: https://EasyMCDM.github.io/
Author: Yanis Labrak & Others
Author-email: yanis.labrak@univ-avignon.fr
License: UNKNOWN
Keywords: python,MCDM,toolkit,easy,Multiple-criteria decision analysis,Multi-Criteria Decision-Making,methods,Multi-Criteria Decision-Making (MCDM)
Platform: UNKNOWN
Requires-Python: >=3.6
Requires-Dist: prettytable
